setup.cfg
setup.py
viajen/__init__.py
viajen/animate.py
viajen/utils.py
viajen.egg-info/PKG-INFO
viajen.egg-info/SOURCES.txt
viajen.egg-info/dependency_links.txt
viajen.egg-info/top_level.txt